aiogram_metrics-2.0.0.dist-info/METADATA
aiogram_metrics-2.0.0.dist-info/WHEEL
aiogram_metrics-2.0.0.dist-info/licenses/LICENSE
aiogram_metrics/__init__.py
aiogram_metrics/api.py
aiogram_metrics/hub.py
aiogram_metrics/public.py
aiogram_metrics/sql.py
aiogram_metrics-2.0.0.dist-info/RECORD
