Metadata-Version: 2.1
Name: aiogram-metrics
Version: 2.0.0
Summary: Message metrics exporter for aiogram framework
Author-Email: benyamin ginzburg <benyamin+git@ginzburg.io>
License: GPL-3.0
Requires-Python: >=3.7
Requires-Dist: aiogram
Requires-Dist: psycopg
Requires-Dist: psycopg-binary
